miyadaiku_theme_bootstrap4/__init__.py
miyadaiku_theme_bootstrap4/__version__.py
miyadaiku_theme_bootstrap4/config.yml
miyadaiku_theme_bootstrap4/externals/css/bootstrap.css
miyadaiku_theme_bootstrap4/externals/css/bootstrap.min.css
miyadaiku_theme_bootstrap4/externals/js/bootstrap.bundle.js
miyadaiku_theme_bootstrap4/externals/js/bootstrap.bundle.min.js
miyadaiku_theme_bootstrap4/externals/js/bootstrap.js
miyadaiku_theme_bootstrap4/externals/js/bootstrap.min.js
miyadaiku_theme_bootstrap4/templates/macros.html
miyadaiku_theme_bootstrap4-1.1.0.dist-info/METADATA
miyadaiku_theme_bootstrap4-1.1.0.dist-info/WHEEL
miyadaiku_theme_bootstrap4-1.1.0.dist-info/top_level.txt
miyadaiku_theme_bootstrap4-1.1.0.dist-info/RECORD
