Metadata-Version: 2.2
Name: miyadaiku_theme_bootstrap4
Version: 1.1.0
Summary: Bootstrap4 files for miyadaiku static site generator
Home-page: https://miyadaiku.github.io/miyadaiku-theme-bootstrap4
Author: Atsuo Ishimoto
License: MIT
Project-URL: Documentation, https://miyadaiku.github.io/
Project-URL: Source, https://miyadaiku.github.io/miyadaiku-theme-bootstrap4
Classifier: Programming Language :: Python :: 3
Classifier: Programming Language :: Python :: 3.13
Classifier: Development Status :: 5 - Production/Stable
Classifier: Environment :: Console
Classifier: Environment :: Web Environment
Classifier: Intended Audience :: Developers
Classifier: Operating System :: OS Independent
Classifier: License :: OSI Approved :: MIT License
Requires-Python: >=3.13
Requires-Dist: miyadaiku>=1.0.0
Requires-Dist: miyadaiku_theme_jquery>=1.0.0
Requires-Dist: miyadaiku_theme_popper_js>=1.0.0
Provides-Extra: dev
Requires-Dist: wheel; extra == "dev"
Requires-Dist: twine; extra == "dev"
Requires-Dist: pytest; extra == "dev"
Requires-Dist: mypy; extra == "dev"
Requires-Dist: black; extra == "dev"
Requires-Dist: flake8; extra == "dev"
Requires-Dist: autoflake; extra == "dev"
